{
    "Ka":{
        "description":"Katakana part",
        "order":"a,i,u,e,o then ka,ki,ku,ke,ko then ga,gi,gu,ge,go and so on",
        "list":[
            "ア","イ","ウ","エ","オ",
            "カ","キ","ク","ケ","コ","ガ","ギ","グ","ゲ","ゴ",
            "サ","シ","ス","セ","ソ","ザ","ジ","ズ","ゼ","ゾ",
            "タ","チ","ツ","テ","ト","ダ","ヂ","ヅ","デ","ド",
            "ナ","ニ","ヌ","ネ","ノ",
            "ハ","ヒ","フ","ヘ","ホ","バ","ビ","ブ","ベ","ボ","パ","ピ","プ","ペ","ポ",
            "マ","ミ","ム","め","モ",
            "ヤ","ユ","ヨ",
            "ラ","リ","ル","レ","ロ",
            "ワ","ヲ",
            "ン"
        ],
        "obsolete":[
            "yi","ye","wi","wu","we"
        ],
        "UTFEqv":[
            "30a2","30a4","30a6","30a8","30aa",
            "30ab","30ad","30af","30b1","30b3","30ac","30ae","30b0","30b2","30b4",
            "30b5","30b7","30b9","30bb","30bd","30b6","30b8","30ba","30bc","30be",
            "30bf","30c1","30c4","30c6","30c8","30c0","30c2","30c5","30c7","30c9",
            "30ca","30cb","30cc","30cd","30ce",
            "30cf","30d2","30d5","30d8","30db","30d0","30d3","30d6","30d9","30dc","30d1","30d4","30d7","30da","30dd",
            "30de","30df","30e0","30e1","30e2",
            "30e4","30e6","30e8",
            "30e9","30ea","30eb","30ec","30ed",
            "30ef","30f2",
            "30f3"
        ]
    },
    "hi":{
        "description":"Hiragana part",
        "order":"a,i,u,e,o then ka,ki,ku,ke,ko then ga,gi,gu,ge,go and so on",
        "list":[
            "あ","い","う","え","お",
            "か","き","く","け","こ","が","ぎ","ぐ","げ","ご",
            "さ","し","す","せ","そ","ざ","じ","ず","ぜ","ぞ",
            "た","ち","つ","て","と","だ","ぢ","づ","で","ど",
            "な","に","ぬ","ね","の",
            "は","ひ","ふ","へ","ほ","ば","び","ぶ","べ","ぼ","ぱ","ぴ","ぷ","ぺ","ぽ",
            "ま","み","む","め","も",
            "や","ゆ","よ",
            "ら","り","る","れ","ろ",
            "わ","を",
            "ん"
        ],
        "obsolete":["yi","ye","wi","wu","we"],
        "UTFEqv":[
            "3042","3044","3046","3048","304a",
            "304b","304d","304f","3051","3053","304c","304e","3050","3052","3054",
            "3055","3057","3059","305b","305d","3056","3058","305a","305c","305e",
            "305f","3061","3064","3066","3068","3060","3062","3065","3067","3069",
            "306a","306b","306c","306d","306e",
            "306f","3072","3075","3078","307b","3070","3073","3076","3079","307c","3071","3074","3077","307a","307d",
            "307e","307f","3080","3081","3082",
            "3084","3086","3088",
            "3089","308a","308b","308c","308d",
            "308f","3092",
            "3093"]
    }
}